{
   "features": [
      {
         "geometry": {
            "coordinates": 
        [
            [
               [
                  32.14590,
                  -3.69987
               ],
               [
                  31.10868,
                  -3.69987
               ],
               [
                  31.10850,
                  -3.96966
               ],
               [
                  32.14618,
                  -3.96701
               ],
               [
                  32.14590,
                  -3.69987
               ]
            ],
	    [
              [
                  32.14619,
                  -3.98530
               ],
               [
                  31.10589,
                  -3.98805
               ],
               [
                  31.13432,
                  -4.46728
               ],
               [
                  32.14641,
                  -4.46394
               ],
               [
                  32.14619,
                  -3.98530
               ]
	    ],
	    [
              [
                  32.14642,
                  -4.48222
               ],
               [
                  31.10831,
                  -4.48736
               ],
               [
                  31.10798,
                  -4.75212
               ],
               [
                  32.14660,
                  -4.75196
               ],
               [
                  32.14642,
                  -4.48222
               ]
	    ]
	],
            "referencesystem": "ICRS",
            "type": "Polygon"
         },
         "properties": 
         {
            "MJD-OBS": 5.468160334590E+04,
            "object": "W1. -3+3",
            "filesize": "675M",
            "identifier": "1013885p",
            "toto":"http://fr.wikipedia.org/wiki/Galaxie_d%27Androm%C3%A8de",
            "title": "IVCG86",
            "quicklook": "http://<ma quicklook>",
            "Physical data": {
               "Diameter": "1,392,539 km",
               "Mean density": "1.41 g/cm3",
               "Mass": "1.989 × 10^30 kg",
               "Luminosity": "3.85 × 10^26 W"
            }
         },
         "services": {"download": {
            "mimetype": "application/fits",
            "url": "http://<toreplace>/1013885p.fits.fz"
         }},
         "type": "Feature"
      }
   ],
   "totalResults": 1,
   "type": "FeatureCollection"
}
